xyalign/__init__.py
xyalign/__main__.py
xyalign/_version.py
xyalign/assemble.py
xyalign/bam.py
xyalign/ploidy.py
xyalign/reftools.py
xyalign/utils.py
xyalign/variants.py
xyalign/xyalign.py
xyalign/scripts/__init__.py
xyalign/scripts/compare_vcfs.py
xyalign/scripts/explore_thresholds.py
xyalign/scripts/plot_count_stats.py
xyalign/scripts/plot_window_differences.py
xyalign/test/__init__.py
xyalign/test/test_assemble.py
xyalign/test/test_bam.py
xyalign/test/test_ploidy.py
xyalign/test/test_reftools.py
xyalign/test/test_utils.py
xyalign/test/test_variants.py
xyalign/test/test_xyalign.py
XYalign-1.1.5.dist-info/LICENSE
XYalign-1.1.5.dist-info/METADATA
XYalign-1.1.5.dist-info/WHEEL
XYalign-1.1.5.dist-info/entry_points.txt
XYalign-1.1.5.dist-info/top_level.txt
XYalign-1.1.5.dist-info/RECORD
