Metadata-Version: 2.1
Name: XYalign
Version: 1.1.5
Summary: Command line tools and python library to infer ploidy, correct for sex chromosome complement, and work with NGS data
Home-page: https://github.com/WilsonSayresLab/XYalign
Author: Tim Webster
Author-email: twebster17@gmail.com
License: GNU General License version 3
Platform: UNKNOWN
Requires-Dist: matplotlib
Requires-Dist: numpy
Requires-Dist: pandas
Requires-Dist: pybedtools
Requires-Dist: pysam
Requires-Dist: scipy
